pyromod/__init__.py
pyromod/config.py
pyromod/config/__init__.py
pyromod/exceptions/__init__.py
pyromod/exceptions/listener_stopped.py
pyromod/exceptions/listener_timeout.py
pyromod/helpers/__init__.py
pyromod/helpers/helpers.py
pyromod/listen/__init__.py
pyromod/listen/callback_query_handler.py
pyromod/listen/chat.py
pyromod/listen/client.py
pyromod/listen/message.py
pyromod/listen/message_handler.py
pyromod/listen/user.py
pyromod/nav/__init__.py
pyromod/nav/pagination.py
pyromod/types/__init__.py
pyromod/types/identifier.py
pyromod/types/listener.py
pyromod/types/listener_types.py
pyromod/utils/__init__.py
pyromod/utils/patch.py
pyromod-3.1.0.dist-info/METADATA
pyromod-3.1.0.dist-info/WHEEL
pyromod-3.1.0.dist-info/licenses/COPYING
pyromod-3.1.0.dist-info/licenses/COPYING.lesser
pyromod-3.1.0.dist-info/licenses/NOTICE
pyromod-3.1.0.dist-info/RECORD
