Metadata-Version: 2.1
Name: pyromod
Version: 3.1.0
Summary: A monkeypatcher add-on for Pyrogram that does conversation handling
Author-email: Pauxis <pauxiscezar@gmail.com>
License-File: COPYING
License-File: COPYING.lesser
License-File: NOTICE
Requires-Python: >=3.8
Requires-Dist: pyrogram>=1.0
